LICENSE
ascii_art/__init__.py
ascii_art/__main__.py
ascii_art_cli-1.4.0.dist-info/entry_points.txt
ascii_art_cli-1.4.0.dist-info/LICENSE
ascii_art_cli-1.4.0.dist-info/WHEEL
ascii_art_cli-1.4.0.dist-info/METADATA
ascii_art_cli-1.4.0.dist-info/RECORD
