Metadata-Version: 2.1
Name: ascii-art-cli
Version: 1.4.0
Summary: ASCII art generator with multiple customization parameters
Home-page: https://github.com/dawsonbooth/ascii-art
License: MIT
Keywords: cli,console,ascii,art,font,image
Author: Dawson Booth
Author-email: pypi@dawsonbooth.com
Requires-Python: >=3.7,<4.0
Classifier: Environment :: Console
Classifier: License :: OSI Approved :: MIT License
Classifier: Operating System :: OS Independent
Classifier: Programming Language :: Python :: 3
Classifier: Programming Language :: Python :: 3.7
Classifier: Programming Language :: Python :: 3.8
Classifier: Programming Language :: Python :: 3.9
Requires-Dist: Pillow (>=8.1.2,<9.0.0)
Project-URL: Documentation, https://dawsonbooth.github.io/ascii-art
Project-URL: Repository, https://github.com/dawsonbooth/ascii-art
